LICENSE
README.md
pyproject.toml
samadhi/__init__.py
samadhi/__main__.py
samadhi/mainwindow.py
samadhi/samadhi.py
samadhi.egg-info/PKG-INFO
samadhi.egg-info/SOURCES.txt
samadhi.egg-info/dependency_links.txt
samadhi.egg-info/requires.txt
samadhi.egg-info/top_level.txt
samadhi/display/dancingdots.py
samadhi/display/layouts.py
samadhi/display/radiantripples.py