Metadata-Version: 2.4
Name: samadhi
Version: 2025.3
Summary: A realtime EEG viewer using novel ways to visualise EEG.
Author-email: Jacob Kanev <jkanev@zoho.com>
Project-URL: homepage, http://samadhi-eeg.info
Project-URL: documentation, https://github.com/jkanev/samadhi
Project-URL: repository, https://github.com/jkanev/samadhi.git
Project-URL: issues, https://github.com/jkanev/samadhi/-/issues
Requires-Python: >=3.10
License-File: LICENSE
Requires-Dist: PyQt6
Requires-Dist: numpy
Requires-Dist: mne_lsl==1.6
Requires-Dist: matplotlib
Requires-Dist: python-osc
Requires-Dist: PyOpenGL
Dynamic: license-file
